seleniumPythonFramework_VeriSoft/__init__.py
seleniumPythonFramework_VeriSoft/data/read_data.py
seleniumPythonFramework_VeriSoft/drivers/BraveDriver.py
seleniumPythonFramework_VeriSoft/drivers/ChromeDriver.py
seleniumPythonFramework_VeriSoft/fixtures/CreateTargetDirectory.py
seleniumPythonFramework_VeriSoft/fixtures/InitGlobalParameters.py
seleniumPythonFramework_VeriSoft/fixtures/Loggers.py
seleniumPythonFramework_VeriSoft/fixtures/OpenSiteWithCRXExtension.py
seleniumPythonFramework_VeriSoft/fixtures/ParameterInjection.py
seleniumPythonFramework_VeriSoft/fixtures/Screenshot.py
seleniumPythonFramework_VeriSoft/fixtures/SetupDriver.py
seleniumPythonFramework_VeriSoft/fixtures/SetupDriverWithMetamaskExtension.py
seleniumPythonFramework_VeriSoft/infra/CustomEventListener.py
seleniumPythonFramework_VeriSoft/utils/HTTPMethods.py
seleniumPythonFramework_VeriSoft/utils/WalletsActionsInterface.py
seleniumPythonFramework_VeriSoft/utils/enum/HTTPStatusCodes.py
seleniumPythonFramework_VeriSoft/utils/enum/NetworkTypes.py
seleniumPythonFramework_VeriSoft/utils/enum/Wallets.py
seleniumpythonframework_verisoft-0.1.6.dist-info/METADATA
seleniumpythonframework_verisoft-0.1.6.dist-info/WHEEL
seleniumpythonframework_verisoft-0.1.6.dist-info/licenses/LICENSE
seleniumpythonframework_verisoft-0.1.6.dist-info/RECORD
