Metadata-Version: 2.1
Name: seleniumPythonFramework_VeriSoft
Version: 0.1.6
Summary: Selenium Python Framework developed by veriSoft
Project-URL: Homepage, https://github.com/pypa/sampleproject
Project-URL: Bug Tracker, https://github.com/pypa/sampleproject/issues
Author-email: Efrat Cohen <efrat.cohen@verisoft.co>
License-File: LICENSE
Classifier: License :: OSI Approved :: MIT License
Classifier: Operating System :: OS Independent
Classifier: Programming Language :: Python :: 3
Requires-Python: >=3.7
